morphapi/__init__.py
morphapi/paths_manager.py
morphapi/api/__init__.py
morphapi/api/allenmorphology.py
morphapi/api/mouselight.py
morphapi/api/mpin_celldb.py
morphapi/api/neuromorphorg.py
morphapi/morphology/__init__.py
morphapi/morphology/cache.py
morphapi/morphology/morphology.py
morphapi/utils/__init__.py
morphapi/utils/data_io.py
morphapi/utils/webqueries.py
morphapi-0.3.2.dist-info/licenses/LICENSE
morphapi-0.3.2.dist-info/METADATA
morphapi-0.3.2.dist-info/WHEEL
morphapi-0.3.2.dist-info/top_level.txt
morphapi-0.3.2.dist-info/RECORD
